{"cameraMode":{"drawMode":0,"name":"Shaded","section":"Shading Mode"},"sceneLighting":true,"audioPlay":false,"sceneViewState":{"m_AlwaysRefresh":false,"showFog":true,"showSkybox":true,"showFlares":true,"showImageEffects":true,"showParticleSystems":true,"showVisualEffectGraphs":true,"m_FxEnabled":true},"in2DMode":false,"pivot":{"x":7.319617748260498,"y":17.39035987854004,"z":117.45046997070313},"rotation":{"x":-0.3973766267299652,"y":0.39765626192092898,"z":-0.1963225156068802,"w":-0.8030872941017151},"size":0.9451881647109985,"orthographic":false}